[
  {
    "type": "select",
    "id": "order",
    "title": "Trier par",
    "options": ["Par Défaut", "Mise à jour", "Populaire", "Titre", "Note"],
    "ids": ["", "update", "popular", "title", "rating"]
  },
  {
    "type": "multi-select",
    "id": "genre",
    "title": "Genres",
    "isGenre": true,
    "options": [
      "Action",
      "Aventure",
      "Comédie",
      "Drame",
      "Ecchi",
      "Fantaisie",
      "Fantasy",
      "Harem",
      "Historique",
      "Horreur",
      "Isekai",
      "Josei",
      "Magie",
      "Manhwa",
      "Mature",
      "Mecha",
      "Mystère",
      "Psychologique",
      "Romance",
      "School Life",
      "Science-Fiction",
      "Seinen",
      "Shoujo",
      "Shounen",
      "Slice of Life",
      "Sports",
      "Surnaturel",
      "Tragédie",
      "Vie scolaire"
    ],
    "ids": [
      "action",
      "adventure",
      "comedy",
      "drama",
      "ecchi",
      "fantasy",
      "fantasy",
      "harem",
      "historical",
      "horror",
      "isekai",
      "josei",
      "magic",
      "manhwa",
      "mature",
      "mecha",
      "mystery",
      "psychological",
      "romance",
      "school-life",
      "sci-fi",
      "seinen",
      "shoujo",
      "shounen",
      "slice-of-life",
      "sports",
      "supernatural",
      "tragedy",
      "school-life"
    ]
  },
  {
    "type": "select",
    "id": "status",
    "title": "Statut",
    "options": ["Tous", "En cours", "Terminé", "En pause", "Abandonné"],
    "ids": ["", "ongoing", "completed", "on-hold", "cancelled"]
  }
]
